pyserver_client/base.py
pyserver_client/interface.py
pyserver_client/server.py
pyserver_client/tool.py
py_server_client-0.0.8.dist-info/METADATA
py_server_client-0.0.8.dist-info/WHEEL
py_server_client-0.0.8.dist-info/top_level.txt
py_server_client-0.0.8.dist-info/RECORD
