Metadata-Version: 2.1
Name: py-server-client
Version: 0.0.8
Summary: The server client for execute bash commands.
Home-page: https://github.com/repen/py-server-client
Author: Andrey Plugin
Author-email: 9keepa@gmail.com
License: MIT
Requires-Python: >=3.6
Requires-Dist: paramiko
Requires-Dist: Jinja2
